.travis.yml
LICENSE
README.rst
bootstrap.py
buildout.cfg
setup.py
docs/HISTORY.txt
quintagroup/__init__.py
quintagroup.robotframework.utils.egg-info/PKG-INFO
quintagroup.robotframework.utils.egg-info/SOURCES.txt
quintagroup.robotframework.utils.egg-info/dependency_links.txt
quintagroup.robotframework.utils.egg-info/entry_points.txt
quintagroup.robotframework.utils.egg-info/namespace_packages.txt
quintagroup.robotframework.utils.egg-info/not-zip-safe
quintagroup.robotframework.utils.egg-info/requires.txt
quintagroup.robotframework.utils.egg-info/top_level.txt
quintagroup/robotframework/__init__.py
quintagroup/robotframework/utils/__init__.py
quintagroup/robotframework/utils/bunchify.py
quintagroup/robotframework/utils/datetimehelper.py
quintagroup/robotframework/utils/rst.py
quintagroup/robotframework/utils/test.rst
quintagroup/robotframework/utils/testfile.rst
quintagroup/robotframework/utils/tests.py