Metadata-Version: 1.1
Name: quintagroup.robotframework.utils
Version: 1.0
Summary: UNKNOWN
Home-page: http://svn.plone.org/svn/collective/
Author: Quintagroup
Author-email: support@quintagroup.com
License: GPL
Keywords: robotframework
Platform: UNKNOWN
Classifier: Programming Language :: Python
